q_developer_wrapper/__init__.py
q_developer_wrapper/q_developer_wrapper.py
q_developer_wrapper-0.0.2.dist-info/licenses/LICENSE
q_developer_wrapper-0.0.2.dist-info/METADATA
q_developer_wrapper-0.0.2.dist-info/WHEEL
q_developer_wrapper-0.0.2.dist-info/top_level.txt
q_developer_wrapper-0.0.2.dist-info/RECORD
