Metadata-Version: 2.4
Name: q_developer_wrapper
Version: 0.0.2
Summary: Python wrapper for Q Developer CLI
Home-page: https://github.com/cornelcroi/q-developer-wrapper
Author: Anthony Bernabeu, Corneliu Croitoru
Author-email: bernabeu.anthony@gmail.com, cornel.croitoru@gmail.com
License: Apache License 2.0
Classifier: Programming Language :: Python :: 3
Classifier: License :: OSI Approved :: Apache Software License
Classifier: Operating System :: OS Independent
Requires-Python: >=3.11
License-File: LICENSE
Dynamic: license-file
